dustydata/__init__.py
dustydata/ds_utils.py
dustydata/test_functions.py
dustydata/wild_west.py
lambdata_dustinstringer-0.0.14.dist-info/LICENSE
lambdata_dustinstringer-0.0.14.dist-info/METADATA
lambdata_dustinstringer-0.0.14.dist-info/WHEEL
lambdata_dustinstringer-0.0.14.dist-info/top_level.txt
lambdata_dustinstringer-0.0.14.dist-info/RECORD
